labelme_toolkit/__init__.py
labelme_toolkit/__main__.py
labelme_toolkit/_formats.py
labelme_toolkit/_json.py
labelme_toolkit/_labelme.py
labelme_toolkit/_migrations.py
labelme_toolkit/_paths.py
labelme_toolkit/_testing.py
labelme_toolkit/_urllib.py
labelme_toolkit/_browsers/__init__.py
labelme_toolkit/_browsers/_images.py
labelme_toolkit/_browsers/css/modern-normalize.min.css
labelme_toolkit/_cli/__init__.py
labelme_toolkit/_cli/_ai_annotate_rectangles.py
labelme_toolkit/_cli/_extract_image.py
labelme_toolkit/_cli/_extract_image_test.py
labelme_toolkit/_cli/_install_pro.py
labelme_toolkit/_cli/_install_pro_test.py
labelme_toolkit/_cli/_json_to_mask.py
labelme_toolkit/_cli/_json_to_mask_test.py
labelme_toolkit/_cli/_json_to_visualization.py
labelme_toolkit/_cli/_json_to_visualization_test.py
labelme_toolkit/_cli/_list_labels.py
labelme_toolkit/_cli/_list_labels_test.py
labelme_toolkit/_data/.gitignore
labelme_toolkit/_data/dogs.json
labelme_toolkit/_data/dogs_rectangle.json
labelme_toolkit/_data/small_dataset.zip
labelme_toolkit/_data/small_dataset/2011_000003.jpg
labelme_toolkit/_data/small_dataset/2011_000003.json
labelme_toolkit/_data/small_dataset/2011_000006.jpg
labelme_toolkit/_data/small_dataset/2011_000006.json
labelme_toolkit/_data/small_dataset/2011_000025.jpg
labelme_toolkit/_data/small_dataset/2011_000025.json
labelme_toolkit/_data/small_dataset.export/classes.txt
labelme_toolkit/_data/small_dataset.export/images/2011_000003.jpg
labelme_toolkit/_data/small_dataset.export/images/2011_000006.jpg
labelme_toolkit/_data/small_dataset.export/images/2011_000025.jpg
labelme_toolkit/_data/small_dataset.export/labels/2011_000003.txt
labelme_toolkit/_data/small_dataset.export/labels/2011_000006.txt
labelme_toolkit/_data/small_dataset.export/labels/2011_000025.txt
labelme_toolkit-1.3.3.dist-info/METADATA
labelme_toolkit-1.3.3.dist-info/WHEEL
labelme_toolkit-1.3.3.dist-info/entry_points.txt
labelme_toolkit-1.3.3.dist-info/RECORD
