Metadata-Version: 2.4
Name: labelme-toolkit
Version: 1.3.3
Summary: Labelme Toolkit
Project-URL: Homepage, https://github.com/labelmeai/toolkit
Author-email: Kentaro Wada <www.kentaro.wada@gmail.com>
License: MIT
Classifier: Development Status :: 3 - Alpha
Classifier: Environment :: Console
Classifier: Intended Audience :: Developers
Classifier: License :: OSI Approved :: MIT License
Classifier: Operating System :: OS Independent
Classifier: Programming Language :: Python
Classifier: Programming Language :: Python :: 3 :: Only
Classifier: Programming Language :: Python :: 3.8
Classifier: Programming Language :: Python :: 3.9
Classifier: Programming Language :: Python :: 3.10
Classifier: Programming Language :: Python :: 3.11
Classifier: Programming Language :: Python :: 3.12
Classifier: Topic :: Software Development :: Libraries :: Python Modules
Requires-Python: >=3.9
Requires-Dist: click
Requires-Dist: imgviz
Requires-Dist: jinja2
Requires-Dist: loguru
Requires-Dist: numpy
Requires-Dist: osam>=0.2.0
Requires-Dist: pillow>=10.1
Provides-Extra: pro
Requires-Dist: labelme-toolkit-pro; extra == 'pro'
Provides-Extra: test
Requires-Dist: build; extra == 'test'
Requires-Dist: mypy; extra == 'test'
Requires-Dist: pytest; extra == 'test'
Requires-Dist: pytest-xdist; extra == 'test'
Requires-Dist: ruff; extra == 'test'
Requires-Dist: twine; extra == 'test'
Requires-Dist: types-pillow; extra == 'test'
Requires-Dist: types-setuptools; extra == 'test'
